{
  "name": "UserPhoto",
  "base": "Disable",
  "idInjection": true,
  "options": {
    "validateUpsert": true
  },
  "properties": {},
  "validations": [],
  "relations": {
    "account": {
      "type": "belongsTo",
      "model": "Account",
      "foreignKey": "",
      "options": {
        "nestRemoting": true
      }
    },
    "photo": {
      "type": "belongsTo",
      "model": "Photo",
      "foreignKey": "",
      "options": {
        "nestRemoting": true
      }
    }
  },
  "acls": [],
  "methods": {}
}
